tests/test_flat_relmvreq.py
tests/test_shiftfile.py
tests/test_wavecal_fuvb_g160m_relmvreq.py
tests/test_dark_nuv.py
tests/test_wavecal_fuva_g130m.py
tests/test_acq_peakxd.py
tests/test_wavecal_fuva_f140l.py
tests/test_nuv_sci_g185m.py
tests/test_flat_fuva.py
tests/test_acq_peakd_fuva.py
tests/conftest.py
tests/test_extract.py
tests/test_wavecal_nuv_g185m.py
tests/test_acq_image.py
tests/test_dark_fuva.py
tests/test_wavecal_nuv_mirrorb.py
tests/test_nuv_sci_g285m.py
tests/test_wavecal_nuv_g285m.py
tests/test_wavecal_nuv_mirrora.py
tests/test_nuv_sci_g230l.py
tests/generate_tempfiles.py
tests/test_cosutil.py
tests/test_wavecal_nuv_g230l.py
tests/helpers.py
tests/test_wavecal_fuvb_g160m.py
tests/test_fuv_timetag.py
tests/test_flat_nuv.py
tests/test_airglow.py
tests/test_acq_search.py
tests/test_acq_peakd_nuv.py
tests/test_dark_fuvb.py
tests/test_wavecal_nuv_g225m.py
tests/test_acq_peakd_both.py
tests/test_average.py
calcos/shiftfile.py
calcos/concurrent.py
calcos/calcos.py
calcos/airglow.py
calcos/version.py
calcos/x1d.py
calcos/phot.py
calcos/calcosparam.py
calcos/timeline.py
calcos/xd_search.py
calcos/dispersion.py
calcos/findshift1.py
calcos/fpavg.py
calcos/accum.py
calcos/wavecal.py
calcos/cosutil.py
calcos/calcos.help
calcos/timetag.py
calcos/trace.py
calcos/average.py
calcos/__init__.py
calcos/getinfo.py
calcos/orbit.py
calcos/burst.py
calcos/osmstep.py
calcos/splittag.py
calcos/ccos.cpython-313-x86_64-linux-gnu.so
calcos/spwcs.py
calcos/extract.py
calcos/pars/calcos.cfgspc
calcos/pars/calcos.cfg
calcos-3.6.1.dist-info/WHEEL
calcos-3.6.1.dist-info/RECORD
calcos-3.6.1.dist-info/top_level.txt
calcos-3.6.1.dist-info/entry_points.txt
calcos-3.6.1.dist-info/METADATA
docs/source/conf.py
