Metadata-Version: 2.4
Name: calcos
Version: 3.6.1
Summary: Calibration software for COS (Cosmic Origins Spectrograph)
Author: Robert Jedrzejewski
Author-email: Phil Hodge <help@stsci.edu>
Classifier: Intended Audience :: Science/Research
Classifier: License :: OSI Approved :: BSD License
Classifier: Operating System :: OS Independent
Classifier: Programming Language :: Python :: 3
Classifier: Programming Language :: C
Classifier: Topic :: Software Development :: Libraries :: Python Modules
Requires-Python: >=3.9
Requires-Dist: astropy>=5.0.4
Requires-Dist: numpy
Requires-Dist: scipy
Requires-Dist: stsci.tools>=4.0.0
Provides-Extra: docs
Requires-Dist: sphinx<7; extra == "docs"
Provides-Extra: test
Requires-Dist: ci-watson; extra == "test"
Requires-Dist: pytest; extra == "test"
Requires-Dist: pytest-cov; extra == "test"
